{
  "address": "webhook_verify_b5d5341a/loop/loop.github/github_pr_event/v0",
  "content": {
    "action": "opened",
    "pr_number": 1,
    "title": "Test PR for webhook verification",
    "author": "tavartar",
    "merged": false,
    "merge_commit_sha": null,
    "html_url": "https://github.com/tavartar/mtvdk-webhook-verify/pull/1",
    "repository": "tavartar/mtvdk-webhook-verify"
  },
  "artifact_type": "github_pr_event",
  "content_hash": "51d15e35fd5162bc783abb22c7f922b748209c5c0fb4e02af84c78448f20a6d7",
  "authorizing_agent": "github-webhook",
  "governance_record": "",
  "created_at": "2026-07-21T12:00:36.898113",
  "metadata": {},
  "status": "committed"
}
